moralis/__init__.py
moralis/aptos_api/__init__.py
moralis/aptos_api/aptos_api.py
moralis/aptos_api/utilities.py
moralis/aptos_api/version.py
moralis/aptos_api/accounts/__init__.py
moralis/aptos_api/accounts/accounts.py
moralis/aptos_api/accounts/api_instance.py
moralis/aptos_api/accounts/get_account.py
moralis/aptos_api/accounts/get_account_module.py
moralis/aptos_api/accounts/get_account_modules.py
moralis/aptos_api/accounts/get_account_resource.py
moralis/aptos_api/accounts/get_account_resources.py
moralis/aptos_api/accounts/get_events_by_creation_number.py
moralis/aptos_api/accounts/get_events_by_event_handle.py
moralis/aptos_api/blocks/__init__.py
moralis/aptos_api/blocks/api_instance.py
moralis/aptos_api/blocks/blocks.py
moralis/aptos_api/blocks/get_block_by_height.py
moralis/aptos_api/blocks/get_block_by_version.py
moralis/aptos_api/coins/__init__.py
moralis/aptos_api/coins/api_instance.py
moralis/aptos_api/coins/coins.py
moralis/aptos_api/coins/get_coin_info_by_coin_type_hashes.py
moralis/aptos_api/coins/get_coin_transfers_by_block_heights.py
moralis/aptos_api/coins/get_coin_transfers_by_coin_type.py
moralis/aptos_api/coins/get_coin_transfers_by_owner_addresses.py
moralis/aptos_api/coins/get_coins_by_creators.py
moralis/aptos_api/coins/get_coins_by_name_range.py
moralis/aptos_api/coins/get_coins_by_symbol_range.py
moralis/aptos_api/coins/get_latest_coins.py
moralis/aptos_api/coins/get_top_holders_by_coin.py
moralis/aptos_api/collections/__init__.py
moralis/aptos_api/collections/api_instance.py
moralis/aptos_api/collections/collections.py
moralis/aptos_api/collections/get_nft_collections.py
moralis/aptos_api/collections/get_nft_collections_by_creator.py
moralis/aptos_api/collections/get_nft_collections_by_ids.py
moralis/aptos_api/nfts/__init__.py
moralis/aptos_api/nfts/api_instance.py
moralis/aptos_api/nfts/get_nft_owners_by_collection.py
moralis/aptos_api/nfts/get_nft_owners_by_tokens.py
moralis/aptos_api/nfts/get_nft_owners_of_collection.py
moralis-0.1.48.dist-info/LICENCE.md
moralis-0.1.48.dist-info/METADATA
moralis-0.1.48.dist-info/WHEEL
moralis-0.1.48.dist-info/top_level.txt
moralis-0.1.48.dist-info/RECORD
