Metadata-Version: 2.1
Name: moralis
Version: 0.1.48
Summary: The official Moralis Python SDK
Keywords: Moralis,Moralis SDK,Moralis Python SDK,Web3,Crypto,Ethereum,Avalanche,Blockchain,Contracts,Eth,Evm,Fantom,Nft,Dapps,Binance,Solana
Requires-Python: >=3.7
License-File: LICENCE.md
Requires-Dist: certifi>=14.5.14
Requires-Dist: frozendict~=2.3.4
Requires-Dist: python-dateutil~=2.8.2
Requires-Dist: typing_extensions~=4.3.0
Requires-Dist: urllib3~=1.26.7
